vectorcraft/__init__.py
vectorcraft/adapters/__init__.py
vectorcraft/adapters/openai.py
vectorcraft/agent_toolkits/__init__.py
vectorcraft/agent_toolkits/ainetwork/__init__.py
vectorcraft/agent_toolkits/ainetwork/toolkit.py
vectorcraft/agent_toolkits/amadeus/__init__.py
vectorcraft/agent_toolkits/amadeus/toolkit.py
vectorcraft/agent_toolkits/azure_cognitive_services.py
vectorcraft/agent_toolkits/base.py
vectorcraft/agent_toolkits/clickup/__init__.py
vectorcraft/agent_toolkits/clickup/toolkit.py
vectorcraft/agent_toolkits/cogniswitch/__init__.py
vectorcraft/agent_toolkits/cogniswitch/toolkit.py
vectorcraft/agent_toolkits/connery/__init__.py
vectorcraft/agent_toolkits/connery/toolkit.py
vectorcraft/agent_toolkits/csv/__init__.py
vectorcraft/agent_toolkits/file_management/__init__.py
vectorcraft/agent_toolkits/file_management/toolkit.py
vectorcraft/agent_toolkits/github/__init__.py
vectorcraft/agent_toolkits/github/toolkit.py
vectorcraft/agent_toolkits/gitlab/__init__.py
vectorcraft/agent_toolkits/gitlab/toolkit.py
vectorcraft/agent_toolkits/gmail/__init__.py
vectorcraft/agent_toolkits/gmail/toolkit.py
vectorcraft/agent_toolkits/jira/__init__.py
vectorcraft/agent_toolkits/jira/toolkit.py
vectorcraft/agent_toolkits/json/__init__.py
vectorcraft/agent_toolkits/json/base.py
vectorcraft/agent_toolkits/json/prompt.py
vectorcraft/agent_toolkits/json/toolkit.py
vectorcraft/agent_toolkits/multion/__init__.py
vectorcraft/agent_toolkits/multion/toolkit.py
vectorcraft/agent_toolkits/nasa/__init__.py
vectorcraft/agent_toolkits/nasa/toolkit.py
vectorcraft/agent_toolkits/nla/__init__.py
vectorcraft/agent_toolkits/nla/tool.py
vectorcraft/agent_toolkits/nla/toolkit.py
vectorcraft/agent_toolkits/office365/__init__.py
vectorcraft/agent_toolkits/office365/toolkit.py
vectorcraft/agent_toolkits/openapi/__init__.py
vectorcraft/agent_toolkits/openapi/base.py
vectorcraft/agent_toolkits/openapi/planner.py
vectorcraft/agent_toolkits/openapi/planner_prompt.py
vectorcraft-0.2.2.dist-info/LICENSE
vectorcraft-0.2.2.dist-info/METADATA
vectorcraft-0.2.2.dist-info/WHEEL
vectorcraft-0.2.2.dist-info/RECORD
